github_social_graph.py
setup.py
github_social_graph.egg-info/PKG-INFO
github_social_graph.egg-info/SOURCES.txt
github_social_graph.egg-info/dependency_links.txt
github_social_graph.egg-info/entry_points.txt
github_social_graph.egg-info/requires.txt
github_social_graph.egg-info/top_level.txt