Metadata-Version: 1.0
Name: github-social-graph
Version: 0.1.0
Summary: Build simple social graphs for GitHub
Home-page: https://github.com/Kagami/github-social-graph
Author: Kagami Hiiragi
Author-email: kagami@genshiken.org
License: CC0
Platform: UNKNOWN
